segment7.v
module segment7( bcd,seg);
     input [3:0] bcd;
     output [7:0] seg;
     reg [7:0] seg;

    always @(bcd)
    begin
        case (bcd) 
            0 : seg = 8'b11000000;
            1 : seg = 8'b11111001;
            2 : seg = 8'b10100100;
            3 : seg = 8'b10110000;
            4 : seg = 8'b10011001;
            5 : seg = 8'b10010010;
            6 : seg = 8'b10000010;
            7 : seg = 8'b11111000;
            8 : seg = 8'b10000000;
            9 : seg = 8'b10010000;
            10: seg = 8'b10100000;
            11: seg = 8'b10100111;
            13: seg = 8'b10100001;
            14: seg = 8'b10000100;
            15: seg = 8'b11110001;
            default : seg = 8'b11111111; 
        endcase
    end
endmodule

segment7_tb.v
module segment7_tb;
    reg [3:0] bcd;
    wire [7:0] seg;
    integer i;
    segment7 uut (.bcd(bcd), 
        .seg(seg));
    initial begin
        for(i = 0;i < 16;i = i+1)
        begin
            bcd = i; 
            #10;
        end     
    end
initial begin
    $dumpfile("segment7.vcd");
    $dumpvars(0, segment7_1);
end
segment7 segment7_1(.bcd(bcd),
          .seg(seg));
endmodule

segment7.vcd
$date
	Fri May 06 03:32:17 2022
$end
$version
	Icarus Verilog
$end
$timescale
	1s
$end
$scope module segment7_tb $end
$scope module segment7_1 $end
$var wire 4 ! bcd [3:0] $end
$var reg 8 " seg [7:0] $end
$upscope $end
$upscope $end
$enddefinitions $end
#0
$dumpvars
b11000000 "
b0 !
$end
#10
b11111001 "
b1 !
#20
b10100100 "
b10 !
#30
b10110000 "
b11 !
#40
b10011001 "
b100 !
#50
b10010010 "
b101 !
#60
b10000010 "
b110 !
#70
b11111000 "
b111 !
#80
b10000000 "
b1000 !
#90
b10010000 "
b1001 !
#100
b10100000 "
b1010 !
#110
b10100111 "
b1011 !
#120
b11111111 "
b1100 !
#130
b10100001 "
b1101 !
#140
b10000100 "
b1110 !
#150
b11110001 "
b1111 !
